ubc/calculator.py
ubc/rates/abstract.py
ubc/rates/openei/__init__.py
ubc/rates/openei/api.py
ubc/rates/openei/schemas.py
ubc/reports.py
ubc-0.0.13.dist-info/WHEEL
ubc-0.0.13.dist-info/METADATA
ubc-0.0.13.dist-info/RECORD
